pyslm/__init__.py
pyslm/core.py
pyslm/version.py
pyslm/visualise.py
pyslm/analysis/__init__.py
pyslm/analysis/iterator.py
pyslm/analysis/utils.py
pyslm/geometry/__init__.py
pyslm/geometry/geometry.py
pyslm/geometry/utils.py
pyslm/hatching/__init__.py
pyslm/hatching/hatching.py
pyslm/hatching/islandHatcher.py
pyslm/hatching/sorting.py
pyslm/hatching/utils.py
pyslm/support/__init__.py
pyslm/support/geometry.py
pyslm/support/gridBlockSupport.py
pyslm/support/render.py
pyslm/support/support.py
pyslm/support/utils.py
src/pyslm/__init__.py
pythonslm-0.6.0.dist-info/METADATA
pythonslm-0.6.0.dist-info/WHEEL
pythonslm-0.6.0.dist-info/licenses/LICENSE
pythonslm-0.6.0.dist-info/RECORD
