Metadata-Version: 2.3
Name: PythonSLM
Version: 0.6.0
Summary: Python Package for Additive Manufacturing and 3D Printing Development
Project-URL: Documentation, https://pyslm.readthedocs.io/en/latest/
Project-URL: Homepage, https://github.com/drlukeparry/pyslm
Project-URL: Source, https://github.com/drylukeparry/pyslm/pyslm/
Project-URL: Tracker, https://github.com/drlukeparry/pyslm/issues
Author-email: Luke Parry <dev@lukeparry.uk>
License:                   GNU LESSER GENERAL PUBLIC LICENSE
License-File: LICENSE
Keywords: 3D Printing,AM,Additive Manufacturing,Geometry,L-PBF,SLM,Selective Laser Melting
Classifier: Programming Language :: Python
Classifier: Programming Language :: Python :: 3.7
Classifier: Programming Language :: Python :: 3.8
Classifier: Programming Language :: Python :: 3.9
Classifier: Programming Language :: Python :: 3.10
Classifier: Programming Language :: Python :: 3.11
Classifier: Programming Language :: Python :: 3.12
Classifier: Topic :: Scientific/Engineering
Requires-Python: >=3.7
Requires-Dist: matplotlib
Requires-Dist: networkx
Requires-Dist: numpy
Requires-Dist: pyclipr
Requires-Dist: rtree
Requires-Dist: scikit-image
Requires-Dist: scipy
Requires-Dist: setuptools
Requires-Dist: shapely
Requires-Dist: trimesh
Provides-Extra: docs
Requires-Dist: autodocsumm; extra == 'docs'
Requires-Dist: cython; extra == 'docs'
Requires-Dist: jupyter; extra == 'docs'
Requires-Dist: matplotlib; extra == 'docs'
Requires-Dist: networkx; extra == 'docs'
Requires-Dist: numpy; extra == 'docs'
Requires-Dist: pyclipr; extra == 'docs'
Requires-Dist: pypandoc; extra == 'docs'
Requires-Dist: scikit-image; extra == 'docs'
Requires-Dist: scipy; extra == 'docs'
Requires-Dist: shapely; extra == 'docs'
Requires-Dist: sphinx; extra == 'docs'
Requires-Dist: sphinx-paramlinks; extra == 'docs'
Requires-Dist: sphinx-rtd-theme; extra == 'docs'
Requires-Dist: trimesh; extra == 'docs'
Provides-Extra: easy
Requires-Dist: colorlog; extra == 'easy'
Requires-Dist: scikit-image; extra == 'easy'
Requires-Dist: setuptools; extra == 'easy'
Requires-Dist: shapely; extra == 'easy'
Requires-Dist: triangle; extra == 'easy'
Requires-Dist: trimesh; extra == 'easy'
Provides-Extra: support
Requires-Dist: manifold3d; extra == 'support'
Requires-Dist: mapbox-earcut; extra == 'support'
Requires-Dist: pyqt5; extra == 'support'
Requires-Dist: setuptools; extra == 'support'
Requires-Dist: shapely; extra == 'support'
Requires-Dist: triangle; extra == 'support'
Requires-Dist: trimesh; extra == 'support'
Requires-Dist: vispy; extra == 'support'
